test/__init__.py
test/server.py
mcp_web_extractor_riversoft-0.1.1.dist-info/METADATA
mcp_web_extractor_riversoft-0.1.1.dist-info/WHEEL
mcp_web_extractor_riversoft-0.1.1.dist-info/entry_points.txt
mcp_web_extractor_riversoft-0.1.1.dist-info/top_level.txt
mcp_web_extractor_riversoft-0.1.1.dist-info/RECORD
